abduct/__init__.py
abduct/compat.py
abduct/stream.py
abduct-2.0.1.dist-info/top_level.txt
abduct-2.0.1.dist-info/METADATA
abduct-2.0.1.dist-info/DESCRIPTION.rst
abduct-2.0.1.dist-info/metadata.json
abduct-2.0.1.dist-info/WHEEL
abduct-2.0.1.dist-info/RECORD
